[
  {
    "url": "images/7000108-cute-love-photography-29620.jpg",
    "caption": "Cute love",
    "display": "block",
    "activeClass": false
  },
  {
    "url": "images/7032388-47-ronin-movie.jpg",
    "caption": "Ronin",
    "display": "none",
    "activeClass": false
  },
  {
    "url": "images/7001760-love-couple-winter.jpg",
    "caption": "Love couple - winter",
    "display": "none",
    "activeClass": false
  },
  {
    "url": "images/7028157-mordor-eye.jpg",
    "caption": "Mordor eye",
    "display": "none",
    "activeClass": false
  },
  {
    "url": "images/7004700-swan-love-heart.jpg",
    "caption": "Swan love heart",
    "activeClass": false
  },
  {
    "url": "images/7040967-mountain-valley.jpg",
    "caption": "Mountain valley",
    "display": "none",
    "activeClass": false
  },
  {
    "url": "images/7039943-white-horses.jpg",
    "caption": "White horses",
    "display": "none",
    "activeClass": false
  },
  {
    "url": "images/7034937-download-thor-2-wallpaper.jpg",
    "caption": "Thor's hammer",
    "display": "none",
    "activeClass": false
  },
  {
    "url": "images/7041205-white-dog.jpg",
    "caption": "White dog",
    "display": "none",
    "activeClass": false
  },
  {
    "url": "images/7041088-titanfall-beta.jpg",
    "caption": "Titan fall",
    "display": "none",
    "activeClass": false
  },
  {
    "url": "images/7041687-polar-bear-baby.jpg",
    "caption": "Polar Bear baby",
    "display": "none",
    "activeClass": false
  },
  {
    "url": "images/7041598-injustice-gods-among-us-wallpaper-for-desktop.jpg",
    "caption": "Injustice - gods among us",
    "display": "none",
    "activeClass": false
  },
  {
    "url": "images/7041335-twelve-apostles-australia.jpg",
    "caption": "Twelve Apostles - Australia",
    "activeClass": false
  },
  {
    "url": "images/7041889-garen-vs-katarina.jpg",
    "caption": "Garen vs Katarina",
    "display": "none",
    "activeClass": false
  },
  {
    "url": "images/7041875-red-rider-winter.jpg",
    "caption": "Red rider - winter",
    "display": "none",
    "activeClass": false
  },
  {
    "url": "images/7041788-trine-2-game.jpg",
    "caption": "Trine 2 game",
    "display": "none",
    "activeClass": false
  }
]